aihpi/__init__.py
aihpi/cli.py
aihpi/core/__init__.py
aihpi/core/config.py
aihpi/core/executor.py
aihpi/examples/__init__.py
aihpi/examples/basic.py
aihpi/examples/monitoring.py
aihpi/examples/train_example.py
aihpi/examples/configs/distributed_config.py
aihpi/examples/configs/llamafactory_config.py
aihpi/examples/configs/local_config.py
aihpi/examples/configs/single_node_config.py
aihpi/monitoring/__init__.py
aihpi/monitoring/monitoring.py
aihpi/tracking/__init__.py
aihpi/tracking/tracking.py
aihpi-0.1.5.dist-info/licenses/LICENSE
aihpi-0.1.5.dist-info/METADATA
aihpi-0.1.5.dist-info/WHEEL
aihpi-0.1.5.dist-info/entry_points.txt
aihpi-0.1.5.dist-info/top_level.txt
aihpi-0.1.5.dist-info/RECORD
