Metadata-Version: 2.4
Name: aihpi
Version: 0.1.5
Summary: AI High Performance Infrastructure - Distributed job submission for SLURM clusters
Home-page: https://github.com/username/aihpi
Author: Felix Boelter
Author-email: Felix Boelter <felix.boelter@hpi.de>
Project-URL: Homepage, https://github.com/aihpi/aihpi-cluster
Project-URL: Bug Reports, https://github.com/aihpi/aihpi-cluster/issues
Project-URL: Source, https://github.com/aihpi/aihpi-cluster
Project-URL: Documentation, https://github.com/aihpi/aihpi-cluster#readme
Keywords: slurm,distributed,training,ai,ml,pytorch,llamafactory
Classifier: Development Status :: 3 - Alpha
Classifier: Intended Audience :: Developers
Classifier: Intended Audience :: Science/Research
Classifier: License :: OSI Approved :: MIT License
Classifier: Operating System :: POSIX :: Linux
Classifier: Programming Language :: Python :: 3
Classifier: Programming Language :: Python :: 3.8
Classifier: Programming Language :: Python :: 3.9
Classifier: Programming Language :: Python :: 3.10
Classifier: Programming Language :: Python :: 3.11
Classifier: Programming Language :: Python :: 3.12
Classifier: Topic :: Scientific/Engineering :: Artificial Intelligence
Classifier: Topic :: System :: Distributed Computing
Requires-Python: >=3.8
License-File: LICENSE
Requires-Dist: submitit>=1.4.0
Provides-Extra: dev
Requires-Dist: pytest>=6.0; extra == "dev"
Requires-Dist: pytest-cov; extra == "dev"
Requires-Dist: pytest-mock; extra == "dev"
Requires-Dist: black; extra == "dev"
Requires-Dist: flake8; extra == "dev"
Requires-Dist: mypy; extra == "dev"
Requires-Dist: isort; extra == "dev"
Provides-Extra: huggingface
Requires-Dist: huggingface_hub; extra == "huggingface"
Provides-Extra: tracking
Requires-Dist: wandb; extra == "tracking"
Requires-Dist: mlflow; extra == "tracking"
Provides-Extra: torch
Requires-Dist: torch; extra == "torch"
Requires-Dist: torchvision; extra == "torch"
Requires-Dist: torchaudio; extra == "torch"
Provides-Extra: metrics
Requires-Dist: tensorboard; extra == "metrics"
Requires-Dist: matplotlib; extra == "metrics"
Requires-Dist: seaborn; extra == "metrics"
Provides-Extra: all
Requires-Dist: huggingface_hub; extra == "all"
Requires-Dist: wandb; extra == "all"
Requires-Dist: mlflow; extra == "all"
Requires-Dist: torch; extra == "all"
Requires-Dist: torchvision; extra == "all"
Requires-Dist: torchaudio; extra == "all"
Requires-Dist: tensorboard; extra == "all"
Requires-Dist: matplotlib; extra == "all"
Requires-Dist: seaborn; extra == "all"
Dynamic: author
Dynamic: home-page
Dynamic: license-file
Dynamic: requires-python
